<?xml version="1.0" encoding="utf-8"?>
<savedqueries xmlns:xsi="http://www.w3.org/2001/XMLSchema-instance">
  <savedquery>
    <IsCustomizable>1</IsCustomizable>
    <CanBeDeleted>0</CanBeDeleted>
    <isquickfindquery>0</isquickfindquery>
    <isprivate>0</isprivate>
    <isdefault>1</isdefault>
    <savedqueryid>{15fefbd3-24d7-473d-9c5a-2fc03baf42f4}</savedqueryid>
    <layoutxml>
      <grid name="pg_exerciserecords" jump="pg_name" select="1" icon="1" preview="0">
        <row name="pg_exerciserecord" id="pg_exerciserecordid">
          <cell name="pg_date" width="150" />
          <cell name="pg_scorenumber" width="150" />
          <cell name="pg_exercise" width="150" />
        </row>
      </grid>
    </layoutxml>
    <querytype>64</querytype>
    <fetchxml>
      <fetch version="1.0" mapping="logical">
        <entity name="pg_exerciserecord">
          <attribute name="pg_exerciserecordid" />
          <filter type="and">
            <condition attribute="statecode" operator="eq" value="0" />
          </filter>
          <attribute name="pg_date" />
          <attribute name="pg_exercise" />
          <attribute name="pg_scorenumber" />
          <order attribute="pg_date" descending="true" />
          <order attribute="pg_exercise" descending="true" />
        </entity>
      </fetch>
    </fetchxml>
    <IntroducedVersion>1.0</IntroducedVersion>
    <LocalizedNames>
      <LocalizedName description="Exercise Record Lookup View" languagecode="1033" />
    </LocalizedNames>
  </savedquery>
</savedqueries>